pyvisflow/__index.py
pyvisflow/__init__.py
pyvisflow/app.py
pyvisflow/core/__init__.py
pyvisflow/core/dataManager.py
pyvisflow/core/jsCode.py
pyvisflow/core/layout.py
pyvisflow/core/optimizers.py
pyvisflow/core/reactive.py
pyvisflow/core/structure.py
pyvisflow/core/components/__init__.py
pyvisflow/core/components/button.py
pyvisflow/core/components/components.py
pyvisflow/core/components/containers.py
pyvisflow/core/components/dataTable.py
pyvisflow/core/components/dataframe.py
pyvisflow/core/components/echart.py
pyvisflow/core/components/file.py
pyvisflow/core/components/icon.py
pyvisflow/core/components/image.py
pyvisflow/core/components/input.py
pyvisflow/core/components/inputNumber.py
pyvisflow/core/components/markdownValue.py
pyvisflow/core/components/plotly.py
pyvisflow/core/components/select.py
pyvisflow/core/components/tabs.py
pyvisflow/core/components/text.py
pyvisflow/core/components/auto_create/__init__.py
pyvisflow/core/components/auto_create/_dataTable.py
pyvisflow/core/components/auto_create/_echart.py
pyvisflow/core/components/auto_create/_input.py
pyvisflow/core/components/auto_create/_inputNumber.py
pyvisflow/core/components/auto_create/_select.py
pyvisflow/core/components/auto_create/_tabs.py
pyvisflow/core/dataset/__init__.py
pyvisflow/core/dataset/dataset.py
pyvisflow/core/dataset/props.py
pyvisflow/core/props/__init__.py
pyvisflow/core/props/absProp.py
pyvisflow/core/props/combineProp.py
pyvisflow/core/props/fns.py
pyvisflow/core/props/methodProp.py
pyvisflow/core/props/objectProp.py
pyvisflow/core/props/typeProp.py
pyvisflow/core/props/valueProp.py
pyvisflow/core/user_utils/__init__.py
pyvisflow/core/user_utils/common.py
pyvisflow/core/user_utils/echart.py
pyvisflow/models/TComponent.py
pyvisflow/models/TConfig.py
pyvisflow/models/TStaticData.py
pyvisflow/models/TWatchInfo.py
pyvisflow/models/__init__.py
pyvisflow/template/index.html
pyvisflow/template/plotly-2.9.0.min.js
pyvisflow/utils/__init__.py
pyvisflow/utils/data_gen.py
pyvisflow-0.3.3.dist-info/LICENSE
pyvisflow-0.3.3.dist-info/METADATA
pyvisflow-0.3.3.dist-info/WHEEL
pyvisflow-0.3.3.dist-info/top_level.txt
pyvisflow-0.3.3.dist-info/RECORD
