Metadata-Version: 2.1
Name: pyvisflow
Version: 0.3.3
Summary: ...
Home-page: https://gitee.com/carson_add/pyvision-next-example
Author: pyvisflow
Author-email: 568166495@qq.com
License: MIT license
Keywords: visflow,vision,flow
Platform: UNKNOWN
Classifier: Intended Audience :: Developers
Classifier: License :: OSI Approved :: MIT License
Classifier: Natural Language :: English
Classifier: Programming Language :: Python :: 3
Classifier: Programming Language :: Python :: 3.6
Classifier: Programming Language :: Python :: 3.7
Classifier: Programming Language :: Python :: 3.8
Requires-Python: >=3.6
Requires-Dist: bs4
Requires-Dist: pandas
